{
  "Afghanistan": "Supreme Leader\u00a0\u2013 Hibatullah Akhundzada",
  "Albania": "Prime Minister\u00a0\u2013 Edi Rama",
  "Algeria": "President\u00a0\u2013 Abdelmadjid Tebboune",
  "Andorra": "Prime Minister\u00a0\u2013 Xavier Espot Zamora",
  "Angola": "President\u00a0\u2013 Jo\u00e3o Louren\u00e7o",
  "Antigua and Barbuda": "Prime Minister\u00a0\u2013 Gaston Browne",
  "Argentina": "President\u00a0\u2013 Alberto Fern\u00e1ndez",
  "Armenia": "Prime Minister\u00a0\u2013 Nikol Pashinyan",
  "Australia": "Prime Minister\u00a0\u2013 Anthony Albanese",
  "Austria": "Chancellor\u00a0\u2013 Karl Nehammer",
  "Azerbaijan": "President\u00a0\u2013 Ilham Aliyev",
  "Bahamas, The": "Prime Minister\u00a0\u2013 Philip Davis",
  "Bahrain": "King\u00a0\u2013 Sheikh Hamad bin Isa Al Khalifa",
  "Bangladesh": "Prime Minister\u00a0\u2013 Sheikh Hasina",
  "Barbados": "Prime Minister\u00a0\u2013 Mia Mottley",
  "Belarus": "President\u00a0\u2013 Alexander Lukashenko[\u03b3]",
  "Belgium": "Prime Minister\u00a0\u2013 Alexander De Croo",
  "Belize": "Prime Minister\u00a0\u2013 Johnny Brice\u00f1o",
  "Benin": "President\u00a0\u2013 Patrice Talon",
  "Bhutan": "Chief Advisor\u00a0\u2013 Chogyal Dago Rigdzin",
  "Bolivia": "President\u00a0\u2013 Luis Arce",
  "Bosnia and Herzegovina": "High Representative\u00a0\u2013 Christian Schmidt[\u03b4]",
  "Presidency": "Presidency[\u03b5]",
  "Botswana": "President\u00a0\u2013 Mokgweetsi Masisi",
  "Brazil": "President\u00a0\u2013 Luiz In\u00e1cio Lula da Silva",
  "Brunei": "Sultan and Prime Minister\u00a0\u2013 Hassanal Bolkiah",
  "Bulgaria": "Prime Minister\u00a0\u2013 Nikolai Denkov",
  "Burkina Faso": "President of the Patriotic Movement for Safeguard and Restoration\u00a0\u2013 Ibrahim Traor\u00e9",
  "President": "President\u00a0\u2013 Mahmoud Abbas[\u03bf]",
  "Burundi": "President\u00a0\u2013 \u00c9variste Ndayishimiye[\u03b3]",
  "Cambodia": "President of the People's Party\u00a0\u2013 Hun Sen[1]",
  "King": "Prime Minister\u00a0\u2013 Hun Manet",
  "Cameroon": "President\u00a0\u2013 Paul Biya[\u03b3]",
  "Canada": "Prime Minister\u00a0\u2013 Justin Trudeau",
  "Cape Verde": "Prime Minister\u00a0\u2013 Ulisses Correia e Silva",
  "Central African Republic": "President\u00a0\u2013 Faustin-Archange Touad\u00e9ra[\u03b3]",
  "Chad": "Transitional President\u00a0\u2013 Mahamat D\u00e9by",
  "Chile": "President\u00a0\u2013 Gabriel Boric",
  "China": "General Secretary of the Communist Party\u00a0\u2013 Xi Jinping",
  "Colombia": "President\u00a0\u2013 Gustavo Petro",
  "Comoros": "President\u00a0\u2013 Azali Assoumani",
  "Congo, Democratic Republic of the": "President\u00a0\u2013 F\u00e9lix Tshisekedi",
  "Congo, Republic of the": "President\u00a0\u2013 Denis Sassou Nguesso",
  "Costa Rica": "President\u00a0\u2013 Rodrigo Chaves Robles",
  "Croatia": "Prime Minister\u00a0\u2013 Andrej Plenkovi\u0107",
  "Cuba": "First Secretary of the Communist Party\u00a0\u2013 Miguel D\u00edaz-Canel",
  "Cyprus": "President\u00a0\u2013 Nikos Christodoulides",
  "Czech Republic": "Prime Minister\u00a0\u2013 Petr Fiala",
  "Denmark": "Prime Minister\u00a0\u2013 Mette Frederiksen",
  "Djibouti": "President\u00a0\u2013 Isma\u00efl Omar Guelleh[\u03b3]",
  "Dominica": "Prime Minister\u00a0\u2013 Roosevelt Skerrit",
  "Dominican Republic": "President\u00a0\u2013 Luis Abinader",
  "East Timor": "Prime Minister\u00a0\u2013 Xanana Gusm\u00e3o",
  "Ecuador": "President\u00a0\u2013 Daniel Noboa",
  "Egypt": "President\u00a0\u2013 Abdel Fattah el-Sisi",
  "El Salvador": "President\u00a0\u2013 Nayib Bukele",
  "Equatorial Guinea": "President\u00a0\u2013 Teodoro Obiang Nguema Mbasogo[\u03b3]",
  "Eritrea": "President\u00a0\u2013 Isaias Afwerki",
  "Estonia": "Prime Minister\u00a0\u2013 Kaja Kallas",
  "Eswatini": "Ngwenyama\u00a0\u2013 Mswati III",
  "Ethiopia": "Prime Minister\u00a0\u2013 Abiy Ahmed",
  "Fiji": "Prime Minister\u00a0\u2013 Sitiveni Rabuka",
  "Finland": "Prime Minister\u00a0\u2013 Petteri Orpo",
  "France": "President\u00a0\u2013 Emmanuel Macron[\u03b1]",
  "Gabon": "Chairman of the Committee for the Transition and Restoration of Institutions\u00a0\u2013 Brice Clotaire Oligui Nguema",
  "Gambia, The": "President\u00a0\u2013 Adama Barrow",
  "Georgia": "Prime Minister\u00a0\u2013 Irakli Garibashvili",
  "Germany": "Chancellor\u00a0\u2013 Olaf Scholz",
  "Ghana": "President\u00a0\u2013 Nana Akufo-Addo",
  "Greece": "Prime Minister\u00a0\u2013 Kyriakos Mitsotakis",
  "Grenada": "Prime Minister\u00a0\u2013 Dickon Mitchell",
  "Guatemala": "President\u00a0\u2013 Alejandro Giammattei",
  "Guinea": "Chairman of the National Committee of Reconciliation and Development\u00a0\u2013 Mamady Doumbouya",
  "Guinea-Bissau": "President\u00a0\u2013 Umaro Sissoco Embal\u00f3",
  "Guyana": "President\u00a0\u2013 Irfaan Ali[\u03b3]",
  "Haiti": "Acting Prime Minister\u00a0\u2013 Ariel Henry",
  "Honduras": "President\u00a0\u2013 Xiomara Castro",
  "Hungary": "Prime Minister\u00a0\u2013 Viktor Orb\u00e1n",
  "Iceland": "Prime Minister\u00a0\u2013 Katr\u00edn Jakobsd\u00f3ttir",
  "India": "Prime Minister\u00a0\u2013 Narendra Modi",
  "Indonesia": "President\u00a0\u2013 Joko Widodo",
  "Iran": "Supreme Leader\u00a0\u2013 Ali Khamenei[\u03b7]",
  "Iraq": "Prime Minister\u00a0\u2013 Mohammed Shia' Al Sudani",
  "Ireland": "Taoiseach\u00a0\u2013 Leo Varadkar",
  "Israel": "Prime Minister\u00a0\u2013 Benjamin Netanyahu",
  "Italy": "Prime Minister\u00a0\u2013 Giorgia Meloni",
  "Ivory Coast": "President\u00a0\u2013 Alassane Ouattara[\u03b3]",
  "Jamaica": "Prime Minister\u00a0\u2013 Andrew Holness",
  "Japan": "Prime Minister\u00a0\u2013 Fumio Kishida",
  "Jordan": "King\u00a0\u2013 Abdullah II",
  "Kazakhstan": "President\u00a0\u2013 Kassym-Jomart Tokayev[\u03b3]",
  "Kenya": "President\u00a0\u2013 William Ruto",
  "Kiribati": "President\u00a0\u2013 Taneti Maamau",
  "Kuwait": "Emir\u00a0\u2013 Sheikh Nawaf Al-Ahmad Al-Jaber Al-Sabah",
  "Kyrgyzstan": "President\u00a0\u2013 Sadyr Japarov[\u03b3]",
  "Laos": "General Secretary of the People's Revolutionary Party\u00a0\u2013 Thongloun Sisoulith",
  "Latvia": "Prime Minister\u00a0\u2013 Evika Sili\u0146a",
  "Lebanon": "Prime Minister\u00a0\u2013 Najib Mikati",
  "Lesotho": "Prime Minister\u00a0\u2013 Sam Matekane",
  "Liberia": "President\u00a0\u2013 George Weah",
  "Libya": "Prime Minister\u00a0\u2013 Abdul Hamid Dbeibeh",
  "Liechtenstein": "Prince Regnant\u00a0\u2013 Hans-Adam II",
  "Regent": "Regent\u00a0\u2013 Hereditary Prince Alois",
  "Lithuania": "Prime Minister\u00a0\u2013 Ingrida \u0160imonyt\u0117",
  "Luxembourg": "Prime Minister\u00a0\u2013 Luc Frieden",
  "Madagascar": "Acting President\u00a0\u2013 Richard Ravalomanana",
  "Malawi": "President\u00a0\u2013 Lazarus Chakwera",
  "Malaysia": "Prime Minister\u00a0\u2013 Anwar Ibrahim",
  "Maldives": "President\u00a0\u2013 Mohamed Muizzu",
  "Mali": "Interim President\u00a0\u2013 Assimi Go\u00efta[\u03b3]",
  "Malta": "Prime Minister\u00a0\u2013 Robert Abela",
  "Marshall Islands": "President\u00a0\u2013 David Kabua",
  "Mauritania": "President\u00a0\u2013 Mohamed Ould Ghazouani",
  "Mauritius": "Prime Minister\u00a0\u2013 Pravind Jugnauth",
  "Mexico": "President\u00a0\u2013 Andr\u00e9s Manuel L\u00f3pez Obrador",
  "Federated States of Micronesia": "President\u00a0\u2013 Wesley Simina",
  "Moldova": "President\u00a0\u2013 Maia Sandu",
  "Monaco": "Sovereign Prince\u00a0\u2013 Albert II",
  "Mongolia": "Prime Minister\u00a0\u2013 Luvsannamsrain Oyun-Erdene",
  "Montenegro": "Prime Minister\u00a0\u2013 Milojko Spaji\u0107",
  "Morocco": "King\u00a0\u2013 Mohammed VI",
  "Mozambique": "President\u00a0\u2013 Filipe Nyusi[\u03b3]",
  "Myanmar": "Chairman of the State Administration Council\u00a0\u2013 Min Aung Hlaing",
  "Namibia": "President\u00a0\u2013 Hage Geingob[\u03b3]",
  "Nauru": "President\u00a0\u2013 David Adeang",
  "Nepal": "Prime Minister\u00a0\u2013 Pushpa Kamal Dahal",
  "Netherlands": "Prime Minister\u00a0\u2013 Mark Rutte",
  "New Zealand": "Prime Minister\u00a0\u2013 Christopher Luxon",
  "Nicaragua": "President\u00a0\u2013 Daniel Ortega",
  "Niger": "President of the National Council for the Safeguard of the Homeland\u00a0\u2013 Abdourahamane Tchiani",
  "Nigeria": "President\u00a0\u2013 Bola Tinubu",
  "North Korea": "General Secretary of the Workers' Party\u00a0\u2013 Kim Jong Un",
  "North Macedonia": "Prime Minister\u00a0\u2013 Dimitar Kova\u010devski",
  "Norway": "Prime Minister\u00a0\u2013 Jonas Gahr St\u00f8re",
  "Oman": "Sultan and Prime Minister\u00a0\u2013 Haitham bin Tariq",
  "Pakistan": "Caretaker Prime Minister\u00a0\u2013 Anwaar ul Haq Kakar",
  "Palau": "President\u00a0\u2013 Surangel Whipps Jr.",
  "Palestine": "President\u00a0\u2013 Mahmoud Abbas",
  "Panama": "President\u00a0\u2013 Laurentino Cortizo",
  "Papua New Guinea": "Prime Minister\u00a0\u2013 James Marape",
  "Paraguay": "President\u00a0\u2013 Santiago Pe\u00f1a",
  "Peru": "President\u00a0\u2013 Dina Boluarte[\u03b3]",
  "Philippines": "President\u00a0\u2013 Bongbong Marcos",
  "Poland": "President\u00a0\u2013 Andrzej Duda",
  "Portugal": "Prime Minister\u00a0\u2013 Ant\u00f3nio Costa",
  "Qatar": "Emir\u00a0\u2013 Sheikh Tamim bin Hamad Al Thani",
  "Romania": "President\u00a0\u2013 Klaus Iohannis",
  "Russia": "President\u00a0\u2013 Vladimir Putin",
  "Rwanda": "President\u00a0\u2013 Paul Kagame[\u03b3]",
  "Saint Kitts and Nevis": "Prime Minister\u00a0\u2013 Terrance Drew",
  "Saint Lucia": "Prime Minister\u00a0\u2013 Philip J. Pierre",
  "Saint Vincent and the Grenadines": "Prime Minister\u00a0\u2013 Ralph Gonsalves",
  "Samoa": "Prime Minister\u00a0\u2013 Fiam\u0113 Naomi Mata\u02bbafa",
  "San Marino": "Captain Regent[\u03ba]\u00a0\u2013 Filippo Tamagnini",
  "S\u00e3o Tom\u00e9 and Pr\u00edncipe": "Prime Minister\u00a0\u2013 Patrice Trovoada",
  "Saudi Arabia": "King\u00a0\u2013 Salman",
  "Senegal": "President\u00a0\u2013 Macky Sall[\u03b3]",
  "Serbia": "President\u00a0\u2013 Aleksandar Vu\u010di\u0107",
  "Seychelles": "President\u00a0\u2013 Wavel Ramkalawan",
  "Sierra Leone": "President\u00a0\u2013 Julius Maada Bio[\u03b3]",
  "Singapore": "Prime Minister\u00a0\u2013 Lee Hsien Loong",
  "Slovakia": "Prime Minister\u00a0\u2013 Robert Fico",
  "Slovenia": "Prime Minister\u00a0\u2013 Robert Golob",
  "Solomon Islands": "Prime Minister\u00a0\u2013 Manasseh Sogavare",
  "Somalia": "President\u00a0\u2013 Hassan Sheikh Mohamud",
  "South Africa": "President\u00a0\u2013 Cyril Ramaphosa",
  "South Korea": "President\u00a0\u2013 Yoon Suk-yeol[\u03b3]",
  "South Sudan": "President\u00a0\u2013 Salva Kiir Mayardit",
  "Spain": "Prime Minister\u00a0\u2013 Pedro S\u00e1nchez",
  "Sri Lanka": "President\u00a0\u2013 Ranil Wickremesinghe[\u03b3]",
  "Sudan": "Transitional Sovereignty Council[\u03bb]",
  "Abdel Fattah al-Burhan": "Abdel Fattah al-Burhan (Chairman)",
  "Suriname": "President\u00a0\u2013 Chan Santokhi",
  "Sweden": "Prime Minister\u00a0\u2013 Ulf Kristersson",
  "Switzerland": "Federal Council[\u03bc]",
  "Syria": "President\u00a0\u2013 Bashar al-Assad[\u03b3]",
  "Tajikistan": "President\u00a0\u2013 Emomali Rahmon[\u03b3]",
  "Tanzania": "President\u00a0\u2013 Samia Suluhu Hassan[\u03b3]",
  "Thailand": "Prime Minister\u00a0\u2013 Srettha Thavisin",
  "Togo": "President\u00a0\u2013 Faure Gnassingb\u00e9[\u03b3]",
  "Tonga": "Prime Minister\u00a0\u2013 Siaosi Sovaleni",
  "Trinidad and Tobago": "Prime Minister\u00a0\u2013 Keith Rowley",
  "Tunisia": "President\u00a0\u2013 Ka\u00efs Sa\u00efed[\u03b3]",
  "Turkey": "President\u00a0\u2013 Recep Tayyip Erdo\u011fan",
  "Turkmenistan": "Chairman of the People's Council\u00a0\u2013 Gurbanguly Berdimuhamedow[13]",
  "Tuvalu": "Prime Minister\u00a0\u2013 Kausea Natano",
  "Uganda": "President\u00a0\u2013 Yoweri Museveni[\u03b3]",
  "Ukraine": "President\u00a0\u2013 Volodymyr Zelenskyy",
  "United Arab Emirates": "President\u00a0\u2013 Sheikh Mohamed bin Zayed Al Nahyan",
  "United Kingdom": "Prime Minister\u00a0\u2013 Rishi Sunak",
  "United States": "President\u00a0\u2013 Joe Biden",
  "Uruguay": "President\u00a0\u2013 Luis Lacalle Pou",
  "Uzbekistan": "President\u00a0\u2013 Shavkat Mirziyoyev[\u03b3]",
  "Vanuatu": "Prime Minister\u00a0\u2013 Charlot Salwai",
  "Vatican City": "Sovereign\u00a0\u2013 Pope Francis",
  "Venezuela": "President\u00a0\u2013 Nicol\u00e1s Maduro",
  "Vietnam": "General Secretary of the Communist Party\u00a0\u2013 Nguy\u1ec5n Ph\u00fa Tr\u1ecdng",
  "Yemen": "Chairman of the Presidential Leadership Council\u00a0\u2013 Rashad al-Alimi",
  "Zambia": "President\u00a0\u2013 Hakainde Hichilema",
  "Zimbabwe": "President\u00a0\u2013 Emmerson Mnangagwa",
  "Cook Islands": "Prime Minister\u00a0\u2013 Mark Brown",
  "Niue": "Premier\u00a0\u2013 Dalton Tagelagi",
  "Abkhazia": "President\u00a0\u2013 Aslan Bzhania",
  "Republic of China": "President\u00a0\u2013 Tsai Ing-wen",
  "Kosovo": "Prime Minister\u00a0\u2013 Albin Kurti",
  "Northern Cyprus": "President\u00a0\u2013 Ersin Tatar",
  "Sahrawi Republic": "General Secretary of the Polisario Front\u00a0\u2013 Brahim Ghali",
  "South Ossetia": "President\u00a0\u2013 Alan Gagloyev",
  "Somaliland": "President\u00a0\u2013 Muse Bihi Abdi",
  "Transnistria": "President\u00a0\u2013 Vadim Krasnoselsky",
  "Supreme Political Council": "Leader of Ansar Allah\u00a0\u2013 Abdul-Malik al-Houthi[14]",
  "Chairman": "Chairman\u00a0\u2013 Mahdi al-Mashat",
  "Syrian National Coalition": "President\u00a0\u2013 Salem al-Meslet",
  "Government of National Stability": "Acting Prime Minister\u00a0\u2013 Osama Hamada[15]",
  "Hamas government in Gaza": "Hamas Chief in the Gaza Strip\u00a0\u2013 Yahya Sinwar",
  "National Unity Government": "Acting President\u00a0\u2013 Duwa Lashi La",
  "Syrian Salvation Government": "Commander-in-Chief of Tahrir al-Sham\u00a0\u2013 Abu Mohammad al-Julani[16]",
  "Mustafa al-Mousa": "Prime Minister\u00a0\u2013 Ali Keda",
  "Coordination Council": "President and Head of the Cabinet\u00a0\u2013 Sviatlana Tsikhanouskaya",
  "National Assembly (2015)": "President of the National Assembly\u00a0\u2013 Dinorah Figuera[17]",
  "European Union": "President of the European Commission\u00a0\u2013 Ursula von der Leyen[19]",
  "Sovereign Military Order of Malta": "Prince and Grand Master\u00a0\u2013 John T. Dunlap"
}